actstats/__init__.py
actstats/core.py
actstats/scipy_decorators.py
actstats/utils/__init__.py
actstats/utils/utils.py
actstats-0.1.1.2.dist-info/licenses/LICENSE
actstats-0.1.1.2.dist-info/METADATA
actstats-0.1.1.2.dist-info/WHEEL
actstats-0.1.1.2.dist-info/top_level.txt
actstats-0.1.1.2.dist-info/RECORD
