Metadata-Version: 2.4
Name: actstats
Version: 0.1.1.2
Summary: Of the Actuary, By the Actuary, For the Actuary: Unifying Statistical Libraries with Actuarial Conventions
Author: Juntao Zhang, Tingting Shi
Author-email: jzhng106@gmail.com
License: Apache License 2.0
Project-URL: Homepage, https://github.com/jzhng105/actuarial_stats
Requires-Python: >=3.8
License-File: LICENSE
Requires-Dist: numpy>=1.21
Requires-Dist: scipy>=1.7
Dynamic: license-file
